{
  "Workflows": [
    {
      "Path": null,
      "SortBy": 0,
      "VariablesSectionElementsOrder": [],
      "ArgumentsSectionElementsOrder": null,
      "ConstantsSectionElementsOrder": [],
      "AddedNamespaces": null
    },
    {
      "Path": "Main.xaml",
      "SortBy": 0,
      "VariablesSectionElementsOrder": [
        "dt_currDate&Sequence_1",
        "dt_&Sequence_1",
        "dt_londa&Sequence_1",
        "dt_lonti&Sequence_1",
        "shda&Sequence_1",
        "dt_shda&Sequence_1",
        "dt_shtim&Sequence_1",
        "dt_ddd&Sequence_1",
        "dt_stdddd&Sequence_1",
        "dt_tt&Sequence_1",
        "dt_yyyy&Sequence_1",
        "dt_yy&Sequence_1",
        "dt_st&Sequence_1"
      ],
      "ArgumentsSectionElementsOrder": [],
      "ConstantsSectionElementsOrder": [],
      "AddedNamespaces": null
    }
  ]
}